volute_xls/__init__.py
volute_xls/excel_creation_tools.py
volute_xls/excel_export_tools.py
volute_xls/excel_extractor.py
volute_xls/excel_metadata.py
volute_xls/excel_operations_mcp.py
volute_xls/excel_operations_optimized.py
volute_xls/excel_operations_tools.py
volute_xls/excel_tools.py
volute_xls/sdk.py
volute_xls/server.py
volute_xls/server_local.py
volute_xls/sheet_capture_tools.py
volute_xls/simple_excel_parser.py
volute_xls/parser/__init__.py
volute_xls/parser/excel_parser.py
volute_xls/tools/__init__.py
volute_xls/tools/charts/__init__.py
volute_xls/tools/charts/excel_chart_tools.py
volute_xls/writer/__init__.py
volute_xls/writer/excel_writer.py
volute_xls-1.4.0.dist-info/licenses/LICENSE
volute_xls-1.4.0.dist-info/METADATA
volute_xls-1.4.0.dist-info/WHEEL
volute_xls-1.4.0.dist-info/entry_points.txt
volute_xls-1.4.0.dist-info/top_level.txt
volute_xls-1.4.0.dist-info/RECORD
