Metadata-Version: 2.4
Name: volute-xls
Version: 1.4.0
Summary: MCP server for Excel analysis and multimodal AI integration - comprehensive metadata extraction and sheet image capture for agents
Home-page: https://gitlab.com/coritan/volute-xls
Author: Coritan
Author-email: Coritan <your-email@example.com>
License: MIT
Project-URL: Homepage, https://gitlab.com/coritan/volute-xls
Project-URL: Repository, https://gitlab.com/coritan/volute-xls.git
Project-URL: Issues, https://gitlab.com/coritan/volute-xls/-/issues
Project-URL: Documentation, https://gitlab.com/coritan/volute-xls/-/blob/main/DEVELOPER_GUIDE.md
Keywords: mcp,excel,ai,agents,desktop,automation,xlwings,multimodal,vision,spreadsheet,image-capture,openpyxl
Classifier: Development Status :: 4 - Beta
Classifier: Intended Audience :: Developers
Classifier: License :: OSI Approved :: MIT License
Classifier: Operating System :: Microsoft :: Windows
Classifier: Operating System :: POSIX :: Linux
Classifier: Operating System :: MacOS
Classifier: Programming Language :: Python :: 3
Classifier: Programming Language :: Python :: 3.8
Classifier: Programming Language :: Python :: 3.9
Classifier: Programming Language :: Python :: 3.10
Classifier: Programming Language :: Python :: 3.11
Classifier: Programming Language :: Python :: 3.12
Classifier: Topic :: Software Development :: Libraries :: Python Modules
Classifier: Topic :: Office/Business :: Office Suites
Classifier: Topic :: Scientific/Engineering :: Artificial Intelligence
Requires-Python: >=3.8
License-File: LICENSE
Requires-Dist: fastmcp>=2.0.0
Requires-Dist: httpx>=0.25.0
Requires-Dist: python-dotenv>=1.0.0
Requires-Dist: pydantic>=2.0.0
Requires-Dist: openpyxl>=3.0.0
Requires-Dist: Pillow>=9.0.0
Requires-Dist: xlwings>=0.30.0
Requires-Dist: pywin32>=306; platform_system == "Windows"
Provides-Extra: windows
Requires-Dist: xlwings>=0.30.0; extra == "windows"
Requires-Dist: pywin32>=306; platform_system == "Windows" and extra == "windows"
Provides-Extra: dev
Requires-Dist: pytest>=7.0.0; extra == "dev"
Requires-Dist: pytest-asyncio>=0.21.0; extra == "dev"
Requires-Dist: build>=0.10.0; extra == "dev"
Requires-Dist: twine>=4.0.0; extra == "dev"
Provides-Extra: full
Requires-Dist: xlwings>=0.30.0; extra == "full"
Requires-Dist: pywin32>=306; platform_system == "Windows" and extra == "full"
Dynamic: author
Dynamic: home-page
Dynamic: license-file
Dynamic: requires-python
